MANIFEST.in
README.rst
setup.py
holiness/__init__.py
holiness.egg-info/PKG-INFO
holiness.egg-info/SOURCES.txt
holiness.egg-info/dependency_links.txt
holiness.egg-info/top_level.txt