Metadata-Version: 1.0
Name: holiness
Version: 0.1
Summary: Produces nice headlines
Home-page: https://github.com/MadaoG/holiness
Author: Daniel Ceglinski
Author-email: danielceglinski@web.de
License: MIT
Platform: UNKNOWN
